pooolify/.git
pooolify/.gitignore
pooolify/LICENSE
pooolify/README.md
pooolify/__init__.py
pooolify/cli.py
pooolify/config.py
pooolify/pyproject.toml
pooolify/requirements-dev.txt
pooolify/requirements.txt
pooolify/uv.lock
pooolify/agents/__init__.py
pooolify/agents/runtime.py
pooolify/api/__init__.py
pooolify/api/routes.py
pooolify/api/security.py
pooolify/api/server.py
pooolify/core/__init__.py
pooolify/core/agent_manager.py
pooolify/core/app.py
pooolify/core/autoload.py
pooolify/core/conversation.py
pooolify/core/conversation_manager.py
pooolify/core/schemas.py
pooolify/core/tool_executor.py
pooolify/db/__init__.py
pooolify/db/ddl.sql
pooolify/docs/image/mainlogo.png
pooolify/examples/__init__.py
pooolify/examples/00_simple_agent/.env.example
pooolify/examples/00_simple_agent/README.md
pooolify/examples/00_simple_agent/__init__.py
pooolify/examples/00_simple_agent/main.py
pooolify/examples/00_simple_agent/pyproject.toml
pooolify/examples/00_simple_agent/agent/index.py
pooolify/examples/00_simple_agent/agent/action_extractor/index.py
pooolify/examples/00_simple_agent/agent/decision_extractor/index.py
pooolify/examples/00_simple_agent/agent/formatter/index.py
pooolify/examples/00_simple_agent/agent/greeter/index.py
pooolify/examples/00_simple_agent/agent/inference/index.py
pooolify/examples/00_simple_agent/agent/issue_extractor/index.py
pooolify/examples/00_simple_agent/agent/prioritizer/index.py
pooolify/examples/00_simple_agent/tools/echo/index.py
pooolify/examples/00_simple_agent/tools/time/index.py
pooolify/examples/00_simple_agent/web/app.js
pooolify/examples/00_simple_agent/web/bg.png
pooolify/examples/00_simple_agent/web/index.html
pooolify/examples/01_web_ui/README.md
pooolify/examples/01_web_ui/index.html
pooolify/examples/01_web_ui/package.json
pooolify/examples/01_web_ui/postcss.config.js
pooolify/examples/01_web_ui/tailwind.config.js
pooolify/examples/01_web_ui/tsconfig.json
pooolify/examples/01_web_ui/vite.config.ts
pooolify-0.3.0.dist-info/METADATA
pooolify-0.3.0.dist-info/WHEEL
pooolify-0.3.0.dist-info/entry_points.txt
pooolify-0.3.0.dist-info/RECORD
