Metadata-Version: 2.4
Name: pooolify
Version: 0.3.0
Summary: pooolify: Code-centric Python framework for multi-agent LLM orchestration with FastAPI + SSE and PostgreSQL persistence
Project-URL: Homepage, https://github.com/Pooolingforest/pooolifyAI
Author: pooolify maintainers
License: MIT
Requires-Python: >=3.10
Requires-Dist: fastapi>=0.110
Requires-Dist: httpx>=0.27
Requires-Dist: openai>=1.40.0
Requires-Dist: psycopg[binary]>=3.2
Requires-Dist: pydantic>=2.6
Requires-Dist: python-dotenv>=1.0
Requires-Dist: uvicorn>=0.30
